Metadata-Version: 1.1
Name: quickgpt
Version: 0.7.4
Summary: A barebones library to make interacting with OpenAI's ChatGPT API much simpler.
Home-page: https://github.com/benbaptist/quickgpt
Author: Ben Baptist
Author-email: me@benbaptist.com
License: UNKNOWN
Platform: UNKNOWN
Classifier: Development Status :: 2 - Pre-Alpha
Classifier: Intended Audience :: Developers
Classifier: License :: OSI Approved :: MIT License
Classifier: Programming Language :: Python :: 3
Classifier: Programming Language :: Python :: 3.7
Classifier: Programming Language :: Python :: 3.8
